atomx/__init__.py
atomx/exceptions.py
atomx/models.py
atomx/utils.py
atomx/version.py
atomx-1.7.dist-info/DESCRIPTION.rst
atomx-1.7.dist-info/METADATA
atomx-1.7.dist-info/RECORD
atomx-1.7.dist-info/WHEEL
atomx-1.7.dist-info/metadata.json
atomx-1.7.dist-info/top_level.txt
atomx-1.7.dist-info/zip-safe
