Metadata-Version: 2.0
Name: atomx
Version: 1.7
Summary: python interface for the atomx api on https://api.atomx.com
Home-page: https://github.com/atomx/atomx-api-python
Author: Spot Media Solutions Sdn. Bhd.
Author-email: daniel@atomx.com
License: ISC
Keywords: atomx rest api
Platform: UNKNOWN
Classifier: Development Status :: 4 - Beta
Classifier: Intended Audience :: Developers
Classifier: License :: OSI Approved :: ISC License (ISCL)
Classifier: Programming Language :: Python :: 2
Classifier: Programming Language :: Python :: 3
Classifier: Topic :: Internet
Classifier: Topic :: Software Development :: Libraries :: Python Modules
Requires-Dist: requests
Provides-Extra: docs
Requires-Dist: sphinx; extra == 'docs'
Provides-Extra: report
Requires-Dist: ipython[notebook]; extra == 'report'
Requires-Dist: matplotlib; extra == 'report'
Requires-Dist: pandas; extra == 'report'
Provides-Extra: test
Requires-Dist: pytest; extra == 'test'
